insurance_claim_model/VERSION
insurance_claim_model/__init__.py
insurance_claim_model/config.yml
insurance_claim_model/pipeline.py
insurance_claim_model/predict.py
insurance_claim_model/train_pipeline.py
insurance_claim_model/config/__init__.py
insurance_claim_model/config/core.py
insurance_claim_model/datasets/__init__.py
insurance_claim_model/datasets/test.csv
insurance_claim_model/processing/__init__.py
insurance_claim_model/processing/data_manager.py
insurance_claim_model/processing/validation.py
insurance_claim_model/trained_models/__init__.py
insurance_claim_model/trained_models/insurance-model-0.0.5.pkl
insurance_claim_model-0.0.5.dist-info/METADATA
insurance_claim_model-0.0.5.dist-info/WHEEL
insurance_claim_model-0.0.5.dist-info/top_level.txt
insurance_claim_model-0.0.5.dist-info/RECORD
