Metadata-Version: 2.1
Name: insurance-claim-model
Version: 0.0.5
Summary: Insurance claim regression model package from kaggle dataset
Home-page: https://github.com/Michael95-m/packaging-insurance-claim-model
Author: min-khant
Author-email: minkhantmgmg.mk19@gmail.com
License: BSD-3
Classifier: License :: OSI Approved :: MIT License
Classifier: Programming Language :: Python
Classifier: Programming Language :: Python :: 3
Classifier: Programming Language :: Python :: 3.7
Classifier: Programming Language :: Python :: 3.8
Classifier: Programming Language :: Python :: 3.9
Classifier: Programming Language :: Python :: 3.10
Classifier: Programming Language :: Python :: 3.11
Classifier: Programming Language :: Python :: Implementation :: CPython
Classifier: Programming Language :: Python :: Implementation :: PyPy
Requires-Python: >=3.7.0
Requires-Dist: pandas (==1.3.5)
Requires-Dist: scikit-learn (==1.0.2)
Requires-Dist: numpy (==1.23.4)
Requires-Dist: tqdm (==4.64.1)
Requires-Dist: feature-engine (==1.5.2)
Requires-Dist: pydantic (==1.10.4)
Requires-Dist: tox (==4.3.5)
Requires-Dist: PyYAML (==6.0)
Requires-Dist: types-PyYAML (==6.0.12.3)
